llm.py
main.py
utils.py
agents/commons.py
agents/deep_research/models.py
agents/deep_research/multi_agent_research.py
agents/deep_research/prompts.py
agents/deep_research/single_agent_research.py
agents/deep_research/tools.py
chunking/commons.py
chunking/recursive.py
cli/__init__.py
cli/codebase.py
cli/research.py
core/agent.py
core/cached_tool.py
core/re_act.py
core/supervisor.py
core/tool.py
khojkar-0.4.0.dist-info/licenses/LICENSE
memory/context.py
memory/memory.py
memory/vector_store.py
scraping/commons.py
scraping/pdf_scraper.py
scraping/trafilatura_scaper.py
scraping/universal_scraper.py
search/arxiv.py
search/commons.py
search/cse_scraper.py
search/duckduckgo.py
search/fallback.py
search/google.py
search/models.py
khojkar-0.4.0.dist-info/METADATA
khojkar-0.4.0.dist-info/WHEEL
khojkar-0.4.0.dist-info/entry_points.txt
khojkar-0.4.0.dist-info/top_level.txt
khojkar-0.4.0.dist-info/RECORD
