Metadata-Version: 2.4
Name: khojkar
Version: 0.4.0
Summary: A tool for conducting deep research on a given topic, using a combination of LLMs, search engines, and other tools.
Requires-Python: <3.13,>=3.12
License-File: LICENSE
Requires-Dist: python-dotenv>=1.1.0
Requires-Dist: click>=8.1.8
Requires-Dist: litellm>=1.65.4
Requires-Dist: pydantic>=2.11.2
Requires-Dist: requests>=2.32.3
Requires-Dist: pypdf>=5.4.0
Requires-Dist: trafilatura>=2.0.0
Requires-Dist: docstring-parser>=0.16
Requires-Dist: playwright>=1.51.0
Requires-Dist: arxiv>=2.2.0
Requires-Dist: diskcache>=5.6.3
Requires-Dist: chromadb>=1.0.4
Requires-Dist: sentence-transformers>=4.0.2
Requires-Dist: aiolimiter>=1.2.1
Requires-Dist: rich>=14.0.0
Requires-Dist: gitpython>=3.1.44
Requires-Dist: jsonref>=1.1.0
Requires-Dist: duckduckgo-search>=8.0.1
Requires-Dist: tiktoken>=0.9.0
Dynamic: license-file
